Metadata-Version: 1.0
Name: othello
Version: 1.0b1
Summary: Implementation of Othello/Reversi for AI course instruction
Home-page: https://github.com/JaimieMurdock/othello
Author: Jaimie Murdock and Eric P. Nichols
Author-email: UNKNOWN
License: UNKNOWN
Download-URL: https://github.com/JaimieMurdock/othello
Keywords: machine learning,games
Platform: UNKNOWN
Classifier: Environment :: Console
Classifier: Programming Language :: Python
Classifier: Programming Language :: Python :: 2
Classifier: Programming Language :: Python :: 2.7
Classifier: Development Status :: 4 - Beta
Classifier: Intended Audience :: Education
Classifier: License :: OSI Approved
Classifier: License :: OSI Approved :: MIT License
Classifier: Operating System :: OS Independent
Classifier: Topic :: Education
Classifier: Topic :: Games/Entertainment :: Board Games
Classifier: Topic :: Scientific/Engineering :: Artificial Intelligence
